README.md
setup.py
addsPy/__init__.py
addsPy/endpoints.py
addsPy.egg-info/PKG-INFO
addsPy.egg-info/SOURCES.txt
addsPy.egg-info/dependency_links.txt
addsPy.egg-info/requires.txt
addsPy.egg-info/top_level.txt