Metadata-Version: 1.1
Name: addsPy
Version: 0.2
Summary: A Python library for working with the ADDS data server
Home-page: https://github.com/jgillmanjr/addsPy
Author: Jason Gillman Jr.
Author-email: jason@rrfaae.com
License: UNKNOWN
Platform: UNKNOWN
Classifier: Development Status :: 3 - Alpha
Classifier: Programming Language :: Python :: 3
